README.md
pyproject.toml
setup.py
mpol/__init__.py
mpol/constants.py
mpol/datasets.py
mpol/dirty_image.py
mpol/gridding.py
mpol/images.py
mpol/losses.py
mpol/utils.py
test/test_fftshift.py
test/test_gridding.py
ynot_astro.egg-info/PKG-INFO
ynot_astro.egg-info/SOURCES.txt
ynot_astro.egg-info/dependency_links.txt
ynot_astro.egg-info/requires.txt
ynot_astro.egg-info/top_level.txt