Metadata-Version: 2.1
Name: ynot-astro
Version: 0.0.1
Summary: Forward Modeling 2D Echellograms
Home-page: https://github.com/gully/ynot
Author: gully
Author-email: igully@gmail.com
License: UNKNOWN
Platform: UNKNOWN
Classifier: Programming Language :: Python :: 3
Classifier: License :: OSI Approved :: MIT License
Classifier: Operating System :: OS Independent
Requires-Python: >=3.5
